README.rst
setup.py
peek_plugin_index_blueprint/__init__.py
peek_plugin_index_blueprint/plugin_package.json
peek_plugin_index_blueprint/rename_plugin.sh
peek_plugin_index_blueprint.egg-info/PKG-INFO
peek_plugin_index_blueprint.egg-info/SOURCES.txt
peek_plugin_index_blueprint.egg-info/dependency_links.txt
peek_plugin_index_blueprint.egg-info/requires.txt
peek_plugin_index_blueprint.egg-info/top_level.txt
peek_plugin_index_blueprint/_private/PluginNames.py
peek_plugin_index_blueprint/_private/__init__.py
peek_plugin_index_blueprint/_private/alembic.ini
peek_plugin_index_blueprint/_private/admin-app/index-blueprint.component.html
peek_plugin_index_blueprint/_private/admin-app/index-blueprint.component.ts
peek_plugin_index_blueprint/_private/admin-app/index-blueprint.module.ts
peek_plugin_index_blueprint/_private/admin-app/edit-thing-type/edit.component.html
peek_plugin_index_blueprint/_private/admin-app/edit-thing-type/edit.component.ts
peek_plugin_index_blueprint/_private/admin-app/status/status.component.html
peek_plugin_index_blueprint/_private/admin-app/status/status.component.ts
peek_plugin_index_blueprint/_private/agent/AgentEntryHook.py
peek_plugin_index_blueprint/_private/agent/__init__.py
peek_plugin_index_blueprint/_private/alembic/__init__.py
peek_plugin_index_blueprint/_private/alembic/env.py
peek_plugin_index_blueprint/_private/alembic/script.py.mako
peek_plugin_index_blueprint/_private/alembic/versions/__init__.py
peek_plugin_index_blueprint/_private/alembic/versions/f9631012ab4b_inital_tables.py
peek_plugin_index_blueprint/_private/both-app/index-blueprint.component.ns.html
peek_plugin_index_blueprint/_private/both-app/index-blueprint.component.ts
peek_plugin_index_blueprint/_private/both-app/index-blueprint.component.web.html
peek_plugin_index_blueprint/_private/both-app/index-blueprint.module.ts
peek_plugin_index_blueprint/_private/both-app/view-thing/view.component.ns.html
peek_plugin_index_blueprint/_private/both-app/view-thing/view.component.ts
peek_plugin_index_blueprint/_private/both-app/view-thing/view.component.web.html
peek_plugin_index_blueprint/_private/both-assets/icon.png
peek_plugin_index_blueprint/_private/both-cfg/index-blueprint-cfg.component.ns.html
