Metadata-Version: 1.1
Name: peek-plugin-index-blueprint
Version: 1.3.0
Summary: Peek Plugin ThingIndex - My first enhancement.
Home-page: https://bitbucket.org/synerty/peek-plugin-index-blueprint
Author: Synerty
Author-email: contact@synerty.com
License: UNKNOWN
Download-URL: https://bitbucket.org/synerty/peek-plugin-index-blueprint/get/1.3.0.zip
Keywords: Peek,Python,Platform,synerty
Platform: UNKNOWN
